LICENSE
README.md
pyproject.toml
setup.cfg
setup.py
voucherify/__init__.py
voucherify/api_client.py
voucherify/api_response.py
voucherify/configuration.py
voucherify/exceptions.py
voucherify/py.typed
voucherify/rest.py
voucherify.egg-info/PKG-INFO
voucherify.egg-info/SOURCES.txt
voucherify.egg-info/dependency_links.txt
voucherify.egg-info/requires.txt
voucherify.egg-info/top_level.txt
voucherify/api/__init__.py
voucherify/api/async_actions_api.py
voucherify/api/bin_api.py
voucherify/api/campaigns_api.py
voucherify/api/categories_api.py
voucherify/api/client_side_api.py
voucherify/api/customers_api.py
voucherify/api/events_api.py
voucherify/api/exports_api.py
voucherify/api/locations_api.py
voucherify/api/loyalties_api.py
voucherify/api/management_api.py
voucherify/api/metadata_schemas_api.py
voucherify/api/orders_api.py
voucherify/api/product_collections_api.py
voucherify/api/products_api.py
voucherify/api/promotions_api.py
voucherify/api/publications_api.py
voucherify/api/qualifications_api.py
voucherify/api/redemptions_api.py
voucherify/api/referrals_api.py
voucherify/api/rewards_api.py
voucherify/api/segments_api.py
voucherify/api/templates_api.py
voucherify/api/validation_rules_api.py
voucherify/api/validations_api.py
voucherify/api/vouchers_api.py
voucherify/models/__init__.py
voucherify/models/access_settings.py
voucherify/models/access_settings_assign.py
voucherify/models/access_settings_campaign_assignments_list.py
voucherify/models/access_settings_unassign.py
voucherify/models/applicable_to.py
voucherify/models/applicable_to_effect.py
voucherify/models/applicable_to_order_item_units_item.py
voucherify/models/applicable_to_result_list.py
voucherify/models/application_details_item.py
voucherify/models/area_store_campaign_assignment.py
voucherify/models/async_action_base.py
voucherify/models/async_action_get_response_body.py
voucherify/models/async_actions_list_response_body.py
voucherify/models/bundle.py
voucherify/models/bundle_identified_item.py
voucherify/models/bundle_missing_item.py
voucherify/models/bus_val_rule_assignment.py
voucherify/models/campaign.py
voucherify/models/campaign_base.py
