Metadata-Version: 2.4
Name: voucherify
Version: 6.0.0
Summary: Voucherify API
Home-page: https://voucherify.io/
Author: Voucherify Team
Author-email: support@voucherify.io
License: MIT
Keywords: OpenAPI,OpenAPI-Generator,Voucherify API
License-File: LICENSE
Requires-Dist: urllib3>=2.5.0
Requires-Dist: python-dateutil
Requires-Dist: pydantic>=2
Requires-Dist: typing-extensions>=4.7.1
Dynamic: author
Dynamic: author-email
Dynamic: description
Dynamic: description-content-type
Dynamic: home-page
Dynamic: keywords
Dynamic: license
Dynamic: license-file
Dynamic: requires-dist
Dynamic: summary
